LICENSE
MANIFEST.in
README.md
setup.cfg
setup.py
tap_pendo/__init__.py
tap_pendo/discover.py
tap_pendo/streams.py
tap_pendo/sync.py
tap_pendo/utils.py
tap_pendo.egg-info/PKG-INFO
tap_pendo.egg-info/SOURCES.txt
tap_pendo.egg-info/dependency_links.txt
tap_pendo.egg-info/entry_points.txt
tap_pendo.egg-info/requires.txt
tap_pendo.egg-info/top_level.txt
tap_pendo/schemas/accounts.json
tap_pendo/schemas/events.json
tap_pendo/schemas/feature_events.json
tap_pendo/schemas/features.json
tap_pendo/schemas/guide_events.json
tap_pendo/schemas/guides.json
tap_pendo/schemas/metadata_accounts.json
tap_pendo/schemas/metadata_visitors.json
tap_pendo/schemas/page_events.json
tap_pendo/schemas/pages.json
tap_pendo/schemas/poll_events.json
tap_pendo/schemas/track_events.json
tap_pendo/schemas/track_types.json
tap_pendo/schemas/visitor_history.json
tap_pendo/schemas/visitors.json
tap_pendo/schemas/shared/metadata.json