Metadata-Version: 2.4
Name: tap-pendo
Version: 1.2.0
Summary: Singer.io tap for extracting data
Home-page: https://github.com/singer-io/tap-pendo
Author: Stitch
Classifier: Programming Language :: Python :: 3 :: Only
License-File: LICENSE
Requires-Dist: singer-python==5.13.2
Requires-Dist: requests
Requires-Dist: pyhumps==1.3.1
Requires-Dist: backoff==1.10.0
Requires-Dist: ijson==3.1.4
Provides-Extra: test
Requires-Dist: pylint==2.5.3; extra == "test"
Requires-Dist: nose; extra == "test"
Provides-Extra: dev
Requires-Dist: ipdb==0.11; extra == "dev"
Dynamic: author
Dynamic: classifier
Dynamic: home-page
Dynamic: license-file
Dynamic: provides-extra
Dynamic: requires-dist
Dynamic: summary
